movie_utils/__init__.py
movie_utils/audio.py
movie_utils/scene_detect.py
movie_utils/utils.py
movie_utils/video.py
movie_utils-0.0.10.dist-info/METADATA
movie_utils-0.0.10.dist-info/WHEEL
movie_utils-0.0.10.dist-info/top_level.txt
movie_utils-0.0.10.dist-info/RECORD
